aiocent/__init__.py
aiocent/core.py
cent/__init__.py
cent/core.py
aiocent-4.1.2.dist-info/METADATA
aiocent-4.1.2.dist-info/WHEEL
aiocent-4.1.2.dist-info/entry_points.txt
aiocent-4.1.2.dist-info/top_level.txt
aiocent-4.1.2.dist-info/RECORD
